{
    "3DBall": {
        "checkpoints": [
            {
                "steps": 49992,
                "file_path": "results\\max-lambda0.9-config3-0\\3DBall\\3DBall-49992.onnx",
                "reward": 1.8333332719224873,
                "creation_time": 1764544552.0705035,
                "auxillary_file_paths": [
                    "results\\max-lambda0.9-config3-0\\3DBall\\3DBall-49992.pt"
                ]
            },
            {
                "steps": 99968,
                "file_path": "results\\max-lambda0.9-config3-0\\3DBall\\3DBall-99968.onnx",
                "reward": 3.2784092236648905,
                "creation_time": 1764544608.0068748,
                "auxillary_file_paths": [
                    "results\\max-lambda0.9-config3-0\\3DBall\\3DBall-99968.pt"
                ]
            },
            {
                "steps": 100021,
                "file_path": "results\\max-lambda0.9-config3-0\\3DBall\\3DBall-100021.onnx",
                "reward": 3.288764174064893,
                "creation_time": 1764544609.391517,
                "auxillary_file_paths": [
                    "results\\max-lambda0.9-config3-0\\3DBall\\3DBall-100021.pt"
                ]
            }
        ],
        "final_checkpoint": {
            "steps": 100021,
            "file_path": "results\\max-lambda0.9-config3-0\\3DBall.onnx",
            "reward": 3.288764174064893,
            "creation_time": 1764544609.391517,
            "auxillary_file_paths": [
                "results\\max-lambda0.9-config3-0\\3DBall\\3DBall-100021.pt"
            ]
        }
    },
    "metadata": {
        "stats_format_version": "0.3.0",
        "mlagents_version": "1.0.0",
        "torch_version": "2.9.0+cpu"
    }
}