{
    "name": "root",
    "gauges": {
        "3DBall.Policy.Entropy.mean": {
            "value": 1.3174270391464233,
            "min": 1.3174270391464233,
            "max": 1.4120728969573975,
            "count": 4
        },
        "3DBall.Policy.Entropy.sum": {
            "value": 15809.1240234375,
            "min": 15809.1240234375,
            "max": 23052.98828125,
            "count": 4
        },
        "3DBall.Environment.EpisodeLength.mean": {
            "value": 999.0,
            "min": 26.233560090702948,
            "max": 999.0,
            "count": 4
        },
        "3DBall.Environment.EpisodeLength.sum": {
            "value": 11988.0,
            "min": 11569.0,
            "max": 12656.0,
            "count": 4
        },
        "3DBall.Step.mean": {
            "value": 47696.0,
            "min": 11977.0,
            "max": 47696.0,
            "count": 4
        },
        "3DBall.Step.sum": {
            "value": 47696.0,
            "min": 11977.0,
            "max": 47696.0,
            "count": 4
        },
        "3DBall.Policy.ExtrinsicValueEstimate.mean": {
            "value": 9.727959632873535,
            "min": 0.18329359591007233,
            "max": 9.727959632873535,
            "count": 4
        },
        "3DBall.Policy.ExtrinsicValueEstimate.sum": {
            "value": 116.73551940917969,
            "min": 80.64918518066406,
            "max": 201.6140594482422,
            "count": 4
        },
        "3DBall.Environment.CumulativeReward.mean": {
            "value": 100.00001525878906,
            "min": 1.6220454302701084,
            "max": 100.00001525878906,
            "count": 4
        },
        "3DBall.Environment.CumulativeReward.sum": {
            "value": 1200.0001831054688,
            "min": 713.6999893188477,
            "max": 1200.0001831054688,
            "count": 4
        },
        "3DBall.Policy.ExtrinsicReward.mean": {
            "value": 100.00001525878906,
            "min": 1.6220454302701084,
            "max": 100.00001525878906,
            "count": 4
        },
        "3DBall.Policy.ExtrinsicReward.sum": {
            "value": 1200.0001831054688,
            "min": 713.6999893188477,
            "max": 1200.0001831054688,
            "count": 4
        },
        "3DBall.Losses.PolicyLoss.mean": {
            "value": 0.2058322457534355,
            "min": 0.2026689838805693,
            "max": 0.2187601592406836,
            "count": 4
        },
        "3DBall.Losses.PolicyLoss.sum": {
            "value": 0.823328983013742,
            "min": 0.8106759355222772,
            "max": 1.0804229160166774,
            "count": 4
        },
        "3DBall.Losses.ValueLoss.mean": {
            "value": 0.06702883655197753,
            "min": 0.06702883655197753,
            "max": 2.359038362037611,
            "count": 4
        },
        "3DBall.Losses.ValueLoss.sum": {
            "value": 0.2681153462079101,
            "min": 0.2681153462079101,
            "max": 11.795191810188054,
            "count": 4
        },
        "3DBall.Policy.LearningRate.mean": {
            "value": 0.0002740824086392,
            "min": 0.0002740824086392,
            "max": 0.00029622750125749995,
            "count": 4
        },
        "3DBall.Policy.LearningRate.sum": {
            "value": 0.0010963296345568,
            "min": 0.0010963296345568,
            "max": 0.0014455680181439997,
            "count": 4
        },
        "3DBall.Policy.Epsilon.mean": {
            "value": 0.28272159999999996,
            "min": 0.28272159999999996,
            "max": 0.297485,
            "count": 4
        },
        "3DBall.Policy.Epsilon.sum": {
            "value": 1.1308863999999998,
            "min": 1.1308863999999998,
            "max": 1.4637120000000001,
            "count": 4
        },
        "3DBall.Policy.Beta.mean": {
            "value": 0.0009144719199999998,
            "min": 0.0009144719199999998,
            "max": 0.00098755075,
            "count": 4
        },
        "3DBall.Policy.Beta.sum": {
            "value": 0.0036578876799999993,
            "min": 0.0036578876799999993,
            "max": 0.004820374400000001,
            "count": 4
        },
        "3DBall.IsTraining.mean": {
            "value": 1.0,
            "min": 1.0,
            "max": 1.0,
            "count": 4
        },
        "3DBall.IsTraining.sum": {
            "value": 1.0,
            "min": 1.0,
            "max": 1.0,
            "count": 4
        }
    },
    "metadata": {
        "timer_format_version": "0.1.0",
        "start_time_seconds": "1764912667",
        "python_version": "3.10.11 (tags/v3.10.11:7d4cc5a, Apr  5 2023, 00:38:17) [MSC v.1929 64 bit (AMD64)]",
        "command_line_arguments": "C:\\Users\\moebn\\Documents\\University\\Project 2-1\\project_2_1_group_7\\venv\\Scripts\\mlagents-learn Config/training_config.yaml --run-id=run_batch_size14_buffer_size2500_learning_rate0.0003_beta0.001_epsilon0.3 --time-scale=20 --env=3DBall_environment/UnityEnvironment.exe --no-graphics",
        "mlagents_version": "1.0.0",
        "mlagents_envs_version": "1.0.0",
        "communication_protocol_version": "1.5.0",
        "pytorch_version": "2.9.1+cpu",
        "numpy_version": "1.23.5",
        "end_time_seconds": "1764912713"
    },
    "total": 45.47567319999507,
    "count": 1,
    "self": 0.19979019998572767,
    "children": {
        "run_training.setup": {
            "total": 0.06548270001076162,
            "count": 1,
            "self": 0.06548270001076162
        },
        "TrainerController.start_learning": {
            "total": 45.21040029999858,
            "count": 1,
            "self": 0.042486399950576015,
            "children": {
                "TrainerController._reset_env": {
                    "total": 6.486949199999799,
                    "count": 1,
                    "self": 6.486949199999799
                },
                "TrainerController.advance": {
                    "total": 38.67436800003634,
                    "count": 4993,
                    "self": 0.043395399407017976,
                    "children": {
                        "env_step": {
                            "total": 14.323436200953438,
                            "count": 4993,
                            "self": 12.45646840207337,
                            "children": {
                                "SubprocessEnvManager._take_step": {
                                    "total": 1.8368520994117716,
                                    "count": 4993,
                                    "self": 0.1300342997565167,
                                    "children": {
                                        "TorchPolicy.evaluate": {
                                            "total": 1.706817799655255,
                                            "count": 4566,
                                            "self": 1.706817799655255
                                        }
                                    }
                                },
                                "workers": {
                                    "total": 0.030115699468296953,
                                    "count": 4993,
                                    "self": 0.0,
                                    "children": {
                                        "worker_root": {
                                            "total": 39.19064759982575,
                                            "count": 4993,
                                            "is_parallel": true,
                                            "self": 29.52399179970962,
                                            "children": {
                                                "steps_from_proto": {
                                                    "total": 0.0002452000044286251,
                                                    "count": 1,
                                                    "is_parallel": true,
                                                    "self": 7.500000356230885e-05,
                                                    "children": {
                                                        "_process_rank_one_or_two_observation": {
                                                            "total": 0.00017020000086631626,
                                                            "count": 2,
                                                            "is_parallel": true,
                                                            "self": 0.00017020000086631626
                                                        }
                                                    }
                                                },
                                                "UnityEnvironment.step": {
                                                    "total": 9.666410600111703,
                                                    "count": 4993,
                                                    "is_parallel": true,
                                                    "self": 0.29477069921267685,
                                                    "children": {
                                                        "UnityEnvironment._generate_step_input": {
                                                            "total": 0.5162502000603126,
                                                            "count": 4993,
                                                            "is_parallel": true,
                                                            "self": 0.5162502000603126
                                                        },
                                                        "communicator.exchange": {
                                                            "total": 8.25652640039334,
                                                            "count": 4993,
                                                            "is_parallel": true,
                                                            "self": 8.25652640039334
                                                        },
                                                        "steps_from_proto": {
                                                            "total": 0.5988633004453732,
                                                            "count": 4993,
                                                            "is_parallel": true,
                                                            "self": 0.2513244011061033,
                                                            "children": {
                                                                "_process_rank_one_or_two_observation": {
                                                                    "total": 0.34753889933926985,
                                                                    "count": 9986,
                                                                    "is_parallel": true,
                                                                    "self": 0.34753889933926985
                                                                }
                                                            }
                                                        }
                                                    }
                                                }
                                            }
                                        }
                                    }
                                }
                            }
                        },
                        "trainer_advance": {
                            "total": 24.307536399675882,
                            "count": 4993,
                            "self": 0.06419629983429331,
                            "children": {
                                "process_trajectory": {
                                    "total": 1.6236511998286005,
                                    "count": 4993,
                                    "self": 1.4843955998221645,
                                    "children": {
                                        "RLTrainer._checkpoint": {
                                            "total": 0.139255600006436,
                                            "count": 1,
                                            "self": 0.139255600006436
                                        }
                                    }
                                },
                                "_update_policy": {
                                    "total": 22.61968890001299,
                                    "count": 17,
                                    "self": 4.050562799850013,
                                    "children": {
                                        "TorchPPOOptimizer.update": {
                                            "total": 18.569126100162975,
                                            "count": 10197,
                                            "self": 18.569126100162975
                                        }
                                    }
                                }
                            }
                        }
                    }
                },
                "TrainerController._save_models": {
                    "total": 0.006596700011868961,
                    "count": 1,
                    "self": 9.499999578110874e-06,
                    "children": {
                        "RLTrainer._checkpoint": {
                            "total": 0.00658720001229085,
                            "count": 1,
                            "self": 0.00658720001229085
                        }
                    }
                }
            }
        }
    }
}