{
    "name": "root",
    "gauges": {
        "3DBall.Policy.Entropy.mean": {
            "value": 1.3833876848220825,
            "min": 1.3833876848220825,
            "max": 1.4248871803283691,
            "count": 4
        },
        "3DBall.Policy.Entropy.sum": {
            "value": 16799.859375,
            "min": 16799.859375,
            "max": 17270.03515625,
            "count": 4
        },
        "3DBall.Environment.EpisodeLength.mean": {
            "value": 44.81749049429658,
            "min": 21.654716981132076,
            "max": 44.81749049429658,
            "count": 4
        },
        "3DBall.Environment.EpisodeLength.sum": {
            "value": 11787.0,
            "min": 11477.0,
            "max": 11787.0,
            "count": 4
        },
        "3DBall.Step.mean": {
            "value": 47999.0,
            "min": 11971.0,
            "max": 47999.0,
            "count": 4
        },
        "3DBall.Step.sum": {
            "value": 47999.0,
            "min": 11971.0,
            "max": 47999.0,
            "count": 4
        },
        "3DBall.Policy.ExtrinsicValueEstimate.mean": {
            "value": 0.827403724193573,
            "min": 0.25200358033180237,
            "max": 0.827403724193573,
            "count": 4
        },
        "3DBall.Policy.ExtrinsicValueEstimate.sum": {
            "value": 217.607177734375,
            "min": 122.97775268554688,
            "max": 217.607177734375,
            "count": 4
        },
        "3DBall.Environment.CumulativeReward.mean": {
            "value": 3.477566712256167,
            "min": 1.162948933350792,
            "max": 3.477566712256167,
            "count": 4
        },
        "3DBall.Environment.CumulativeReward.sum": {
            "value": 914.6000453233719,
            "min": 615.199985742569,
            "max": 914.6000453233719,
            "count": 4
        },
        "3DBall.Policy.ExtrinsicReward.mean": {
            "value": 3.477566712256167,
            "min": 1.162948933350792,
            "max": 3.477566712256167,
            "count": 4
        },
        "3DBall.Policy.ExtrinsicReward.sum": {
            "value": 914.6000453233719,
            "min": 615.199985742569,
            "max": 914.6000453233719,
            "count": 4
        },
        "3DBall.Losses.PolicyLoss.mean": {
            "value": 0.1091967181190108,
            "min": 0.1091967181190108,
            "max": 0.11067934388348147,
            "count": 4
        },
        "3DBall.Losses.PolicyLoss.sum": {
            "value": 0.1091967181190108,
            "min": 0.1091967181190108,
            "max": 0.11067934388348147,
            "count": 4
        },
        "3DBall.Losses.ValueLoss.mean": {
            "value": 0.5421551371804135,
            "min": 0.20635974855045153,
            "max": 0.5421551371804135,
            "count": 4
        },
        "3DBall.Losses.ValueLoss.sum": {
            "value": 0.5421551371804135,
            "min": 0.20635974855045153,
            "max": 0.5421551371804135,
            "count": 4
        },
        "3DBall.Policy.LearningRate.mean": {
            "value": 0.0004611290077742,
            "min": 0.0004611290077742,
            "max": 0.0004902930019414,
            "count": 4
        },
        "3DBall.Policy.LearningRate.sum": {
            "value": 0.0004611290077742,
            "min": 0.0004611290077742,
            "max": 0.0004902930019414,
            "count": 4
        },
        "3DBall.Policy.Epsilon.mean": {
            "value": 0.2383387,
            "min": 0.2383387,
            "max": 0.24708789999999997,
            "count": 4
        },
        "3DBall.Policy.Epsilon.sum": {
            "value": 0.2383387,
            "min": 0.2383387,
            "max": 0.24708789999999997,
            "count": 4
        },
        "3DBall.Policy.Beta.mean": {
            "value": 0.0012919386200000002,
            "min": 0.0012919386200000002,
            "max": 0.0013730145399999997,
            "count": 4
        },
        "3DBall.Policy.Beta.sum": {
            "value": 0.0012919386200000002,
            "min": 0.0012919386200000002,
            "max": 0.0013730145399999997,
            "count": 4
        },
        "3DBall.IsTraining.mean": {
            "value": 1.0,
            "min": 1.0,
            "max": 1.0,
            "count": 4
        },
        "3DBall.IsTraining.sum": {
            "value": 1.0,
            "min": 1.0,
            "max": 1.0,
            "count": 4
        }
    },
    "metadata": {
        "timer_format_version": "0.1.0",
        "start_time_seconds": "1765148928",
        "python_version": "3.10.11 (tags/v3.10.11:7d4cc5a, Apr  5 2023, 00:38:17) [MSC v.1929 64 bit (AMD64)]",
        "command_line_arguments": "C:\\Users\\moebn\\Documents\\University\\Project 2-1\\project_2_1_group_7\\venv\\Scripts\\mlagents-learn Config/training_config.yaml --run-id=run_batch_size53_buffer_size9700_learning_rate0.0005_beta0.0014_epsilon0.25 --time-scale=20 --env=3DBall_environment/UnityEnvironment.exe --no-graphics",
        "mlagents_version": "1.0.0",
        "mlagents_envs_version": "1.0.0",
        "communication_protocol_version": "1.5.0",
        "pytorch_version": "2.9.1+cpu",
        "numpy_version": "1.23.5",
        "end_time_seconds": "1765148961"
    },
    "total": 33.1570742999902,
    "count": 1,
    "self": 0.18937609996646643,
    "children": {
        "run_training.setup": {
            "total": 0.07441240001935512,
            "count": 1,
            "self": 0.07441240001935512
        },
        "TrainerController.start_learning": {
            "total": 32.89328580000438,
            "count": 1,
            "self": 0.04762909884448163,
            "children": {
                "TrainerController._reset_env": {
                    "total": 7.490335200011032,
                    "count": 1,
                    "self": 7.490335200011032
                },
                "TrainerController.advance": {
                    "total": 25.349085401161574,
                    "count": 5529,
                    "self": 0.045774202939355746,
                    "children": {
                        "env_step": {
                            "total": 14.156287998630432,
                            "count": 5529,
                            "self": 12.628144300688291,
                            "children": {
                                "SubprocessEnvManager._take_step": {
                                    "total": 1.4954892990645021,
                                    "count": 5529,
                                    "self": 0.12096679979003966,
                                    "children": {
                                        "TorchPolicy.evaluate": {
                                            "total": 1.3745224992744625,
                                            "count": 4234,
                                            "self": 1.3745224992744625
                                        }
                                    }
                                },
                                "workers": {
                                    "total": 0.032654398877639323,
                                    "count": 5529,
                                    "self": 0.0,
                                    "children": {
                                        "worker_root": {
                                            "total": 25.922055699658813,
                                            "count": 5529,
                                            "is_parallel": true,
                                            "self": 16.235419498814736,
                                            "children": {
                                                "steps_from_proto": {
                                                    "total": 0.0002796999760903418,
                                                    "count": 1,
                                                    "is_parallel": true,
                                                    "self": 0.00010549998842179775,
                                                    "children": {
                                                        "_process_rank_one_or_two_observation": {
                                                            "total": 0.00017419998766854405,
                                                            "count": 2,
                                                            "is_parallel": true,
                                                            "self": 0.00017419998766854405
                                                        }
                                                    }
                                                },
                                                "UnityEnvironment.step": {
                                                    "total": 9.686356500867987,
                                                    "count": 5529,
                                                    "is_parallel": true,
                                                    "self": 0.3457029992423486,
                                                    "children": {
                                                        "UnityEnvironment._generate_step_input": {
                                                            "total": 0.5134528006019536,
                                                            "count": 5529,
                                                            "is_parallel": true,
                                                            "self": 0.5134528006019536
                                                        },
                                                        "communicator.exchange": {
                                                            "total": 8.176591800758615,
                                                            "count": 5529,
                                                            "is_parallel": true,
                                                            "self": 8.176591800758615
                                                        },
                                                        "steps_from_proto": {
                                                            "total": 0.6506089002650697,
                                                            "count": 5529,
                                                            "is_parallel": true,
                                                            "self": 0.28308700109482743,
                                                            "children": {
                                                                "_process_rank_one_or_two_observation": {
                                                                    "total": 0.36752189917024225,
                                                                    "count": 11058,
                                                                    "is_parallel": true,
                                                                    "self": 0.36752189917024225
                                                                }
                                                            }
                                                        }
                                                    }
                                                }
                                            }
                                        }
                                    }
                                }
                            }
                        },
                        "trainer_advance": {
                            "total": 11.147023199591786,
                            "count": 5529,
                            "self": 0.05290719956974499,
                            "children": {
                                "process_trajectory": {
                                    "total": 2.3487375999975484,
                                    "count": 5529,
                                    "self": 2.270358799985843,
                                    "children": {
                                        "RLTrainer._checkpoint": {
                                            "total": 0.07837880001170561,
                                            "count": 1,
                                            "self": 0.07837880001170561
                                        }
                                    }
                                },
                                "_update_policy": {
                                    "total": 8.745378400024492,
                                    "count": 5,
                                    "self": 3.4825004999584053,
                                    "children": {
                                        "TorchPPOOptimizer.update": {
                                            "total": 5.262877900066087,
                                            "count": 2748,
                                            "self": 5.262877900066087
                                        }
                                    }
                                }
                            }
                        }
                    }
                },
                "TrainerController._save_models": {
                    "total": 0.0062360999872908,
                    "count": 1,
                    "self": 9.99998883344233e-06,
                    "children": {
                        "RLTrainer._checkpoint": {
                            "total": 0.006226099998457357,
                            "count": 1,
                            "self": 0.006226099998457357
                        }
                    }
                }
            }
        }
    }
}