{
    "name": "root",
    "gauges": {
        "3DBall.Policy.Entropy.mean": {
            "value": 1.407005786895752,
            "min": 1.407005786895752,
            "max": 1.4203885793685913,
            "count": 4
        },
        "3DBall.Policy.Entropy.sum": {
            "value": 17964.650390625,
            "min": 17073.48046875,
            "max": 17964.650390625,
            "count": 4
        },
        "3DBall.Environment.EpisodeLength.mean": {
            "value": 85.86619718309859,
            "min": 22.16377649325626,
            "max": 85.86619718309859,
            "count": 4
        },
        "3DBall.Environment.EpisodeLength.sum": {
            "value": 12193.0,
            "min": 11503.0,
            "max": 12193.0,
            "count": 4
        },
        "3DBall.Step.mean": {
            "value": 47754.0,
            "min": 11999.0,
            "max": 47754.0,
            "count": 4
        },
        "3DBall.Step.sum": {
            "value": 47754.0,
            "min": 11999.0,
            "max": 47754.0,
            "count": 4
        },
        "3DBall.Policy.ExtrinsicValueEstimate.mean": {
            "value": 2.2483110427856445,
            "min": 0.17077042162418365,
            "max": 2.2483110427856445,
            "count": 4
        },
        "3DBall.Policy.ExtrinsicValueEstimate.sum": {
            "value": 317.0118408203125,
            "min": 88.45907592773438,
            "max": 317.0118408203125,
            "count": 4
        },
        "3DBall.Environment.CumulativeReward.mean": {
            "value": 7.257447834555984,
            "min": 1.2164092365379038,
            "max": 7.257447834555984,
            "count": 4
        },
        "3DBall.Environment.CumulativeReward.sum": {
            "value": 1023.3001446723938,
            "min": 630.0999845266342,
            "max": 1023.3001446723938,
            "count": 4
        },
        "3DBall.Policy.ExtrinsicReward.mean": {
            "value": 7.257447834555984,
            "min": 1.2164092365379038,
            "max": 7.257447834555984,
            "count": 4
        },
        "3DBall.Policy.ExtrinsicReward.sum": {
            "value": 1023.3001446723938,
            "min": 630.0999845266342,
            "max": 1023.3001446723938,
            "count": 4
        },
        "3DBall.Losses.PolicyLoss.mean": {
            "value": 0.10726419162968626,
            "min": 0.10514193749476757,
            "max": 0.11705016043936453,
            "count": 4
        },
        "3DBall.Losses.PolicyLoss.sum": {
            "value": 0.429056766518745,
            "min": 0.429056766518745,
            "max": 0.5561536522787143,
            "count": 4
        },
        "3DBall.Losses.ValueLoss.mean": {
            "value": 3.656362979965766,
            "min": 0.5677999073097892,
            "max": 3.656362979965766,
            "count": 4
        },
        "3DBall.Losses.ValueLoss.sum": {
            "value": 14.625451919863064,
            "min": 2.628114363825913,
            "max": 14.625451919863064,
            "count": 4
        },
        "3DBall.Policy.LearningRate.mean": {
            "value": 9.16401083599e-05,
            "min": 9.16401083599e-05,
            "max": 9.874350125650001e-05,
            "count": 4
        },
        "3DBall.Policy.LearningRate.sum": {
            "value": 0.0003665604334396,
            "min": 0.0003665604334396,
            "max": 0.0004823998176002001,
            "count": 4
        },
        "3DBall.Policy.Epsilon.mean": {
            "value": 0.14582005,
            "min": 0.14582005,
            "max": 0.14937174999999997,
            "count": 4
        },
        "3DBall.Policy.Epsilon.sum": {
            "value": 0.5832802,
            "min": 0.5832802,
            "max": 0.7411999,
            "count": 4
        },
        "3DBall.Policy.Beta.mean": {
            "value": 0.00110051719,
            "min": 0.00110051719,
            "max": 0.00118504765,
            "count": 4
        },
        "3DBall.Policy.Beta.sum": {
            "value": 0.00440206876,
            "min": 0.00440206876,
            "max": 0.005790557619999999,
            "count": 4
        },
        "3DBall.IsTraining.mean": {
            "value": 1.0,
            "min": 1.0,
            "max": 1.0,
            "count": 4
        },
        "3DBall.IsTraining.sum": {
            "value": 1.0,
            "min": 1.0,
            "max": 1.0,
            "count": 4
        }
    },
    "metadata": {
        "timer_format_version": "0.1.0",
        "start_time_seconds": "1765131120",
        "python_version": "3.10.11 (tags/v3.10.11:7d4cc5a, Apr  5 2023, 00:38:17) [MSC v.1929 64 bit (AMD64)]",
        "command_line_arguments": "C:\\Users\\moebn\\Documents\\University\\Project 2-1\\project_2_1_group_7\\venv\\Scripts\\mlagents-learn Config/training_config.yaml --run-id=run_batch_size53_buffer_size2500_learning_rate0.0001_beta0.0012_epsilon0.15 --time-scale=20 --env=3DBall_environment/UnityEnvironment.exe --no-graphics",
        "mlagents_version": "1.0.0",
        "mlagents_envs_version": "1.0.0",
        "communication_protocol_version": "1.5.0",
        "pytorch_version": "2.9.1+cpu",
        "numpy_version": "1.23.5",
        "end_time_seconds": "1765131149"
    },
    "total": 28.647559300006833,
    "count": 1,
    "self": 0.15585009998176247,
    "children": {
        "run_training.setup": {
            "total": 0.07019030000083148,
            "count": 1,
            "self": 0.07019030000083148
        },
        "TrainerController.start_learning": {
            "total": 28.42151890002424,
            "count": 1,
            "self": 0.04547000033198856,
            "children": {
                "TrainerController._reset_env": {
                    "total": 3.351463499973761,
                    "count": 1,
                    "self": 3.351463499973761
                },
                "TrainerController.advance": {
                    "total": 25.01791289972607,
                    "count": 5427,
                    "self": 0.044397999212378636,
                    "children": {
                        "env_step": {
                            "total": 14.327753000892699,
                            "count": 5427,
                            "self": 12.770694402483059,
                            "children": {
                                "SubprocessEnvManager._take_step": {
                                    "total": 1.5247742992069107,
                                    "count": 5427,
                                    "self": 0.12293259837315418,
                                    "children": {
                                        "TorchPolicy.evaluate": {
                                            "total": 1.4018417008337565,
                                            "count": 4377,
                                            "self": 1.4018417008337565
                                        }
                                    }
                                },
                                "workers": {
                                    "total": 0.03228429920272902,
                                    "count": 5427,
                                    "self": 0.0,
                                    "children": {
                                        "worker_root": {
                                            "total": 25.550665799702983,
                                            "count": 5427,
                                            "is_parallel": true,
                                            "self": 15.7906466985296,
                                            "children": {
                                                "steps_from_proto": {
                                                    "total": 0.00024339999072253704,
                                                    "count": 1,
                                                    "is_parallel": true,
                                                    "self": 7.680000271648169e-05,
                                                    "children": {
                                                        "_process_rank_one_or_two_observation": {
                                                            "total": 0.00016659998800605536,
                                                            "count": 2,
                                                            "is_parallel": true,
                                                            "self": 0.00016659998800605536
                                                        }
                                                    }
                                                },
                                                "UnityEnvironment.step": {
                                                    "total": 9.759775701182662,
                                                    "count": 5427,
                                                    "is_parallel": true,
                                                    "self": 0.32115200004773214,
                                                    "children": {
                                                        "UnityEnvironment._generate_step_input": {
                                                            "total": 0.5210289005481172,
                                                            "count": 5427,
                                                            "is_parallel": true,
                                                            "self": 0.5210289005481172
                                                        },
                                                        "communicator.exchange": {
                                                            "total": 8.272994900064077,
                                                            "count": 5427,
                                                            "is_parallel": true,
                                                            "self": 8.272994900064077
                                                        },
                                                        "steps_from_proto": {
                                                            "total": 0.644599900522735,
                                                            "count": 5427,
                                                            "is_parallel": true,
                                                            "self": 0.27707610206562094,
                                                            "children": {
                                                                "_process_rank_one_or_two_observation": {
                                                                    "total": 0.367523798457114,
                                                                    "count": 10854,
                                                                    "is_parallel": true,
                                                                    "self": 0.367523798457114
                                                                }
                                                            }
                                                        }
                                                    }
                                                }
                                            }
                                        }
                                    }
                                }
                            }
                        },
                        "trainer_advance": {
                            "total": 10.645761899620993,
                            "count": 5427,
                            "self": 0.05440390089643188,
                            "children": {
                                "process_trajectory": {
                                    "total": 2.0269585987553,
                                    "count": 5427,
                                    "self": 1.8878835987707134,
                                    "children": {
                                        "RLTrainer._checkpoint": {
                                            "total": 0.1390749999845866,
                                            "count": 1,
                                            "self": 0.1390749999845866
                                        }
                                    }
                                },
                                "_update_policy": {
                                    "total": 8.564399399969261,
                                    "count": 19,
                                    "self": 3.49434789957013,
                                    "children": {
                                        "TorchPPOOptimizer.update": {
                                            "total": 5.070051500399131,
                                            "count": 2712,
                                            "self": 5.070051500399131
                                        }
                                    }
                                }
                            }
                        }
                    }
                },
                "TrainerController._save_models": {
                    "total": 0.006672499992419034,
                    "count": 1,
                    "self": 9.399984264746308e-06,
                    "children": {
                        "RLTrainer._checkpoint": {
                            "total": 0.006663100008154288,
                            "count": 1,
                            "self": 0.006663100008154288
                        }
                    }
                }
            }
        }
    }
}